face_alignment_edit/__init__.py
face_alignment_edit/api.py
face_alignment_edit/utils.py
face_alignment_edit/detection/__init__.py
face_alignment_edit/detection/core.py
face_alignment_edit/detection/blazeface/__init__.py
face_alignment_edit/detection/blazeface/blazeface_detector.py
face_alignment_edit/detection/blazeface/detect.py
face_alignment_edit/detection/blazeface/net_blazeface.py
face_alignment_edit/detection/blazeface/utils.py
face_alignment_edit/detection/dlib/__init__.py
face_alignment_edit/detection/dlib/dlib_detector.py
face_alignment_edit/detection/folder/__init__.py
face_alignment_edit/detection/folder/folder_detector.py
face_alignment_edit/detection/sfd/__init__.py
face_alignment_edit/detection/sfd/bbox.py
face_alignment_edit/detection/sfd/detect.py
face_alignment_edit/detection/sfd/net_s3fd.py
face_alignment_edit/detection/sfd/sfd_detector.py
face_alignment_edit-1.3.3.3.dist-info/LICENSE
face_alignment_edit-1.3.3.3.dist-info/METADATA
face_alignment_edit-1.3.3.3.dist-info/WHEEL
face_alignment_edit-1.3.3.3.dist-info/top_level.txt
face_alignment_edit-1.3.3.3.dist-info/zip-safe
face_alignment_edit-1.3.3.3.dist-info/RECORD
