Metadata-Version: 2.1
Name: face-alignment-edit
Version: 1.3.3.3
Summary: Detector 2D or 3D face landmarks from Python
Home-page: https://github.com/1adrianb/face-alignment
Author: Adrian Bulat
Author-email: adrian@adrianbulat.com
License: BSD
Platform: UNKNOWN
Classifier: Development Status :: 5 - Production/Stable
Classifier: Operating System :: OS Independent
Classifier: License :: OSI Approved :: BSD License
Classifier: Natural Language :: English
Classifier: Programming Language :: Python :: 3
Classifier: Programming Language :: Python :: 3.3
Classifier: Programming Language :: Python :: 3.4
Classifier: Programming Language :: Python :: 3.5
Classifier: Programming Language :: Python :: 3.6
Classifier: Programming Language :: Python :: 3.7
Classifier: Programming Language :: Python :: 3.8
Requires-Python: >=3
License-File: LICENSE
Requires-Dist: torch
Requires-Dist: numpy
Requires-Dist: scipy (>=0.17)
Requires-Dist: scikit-image
Requires-Dist: opencv-python
Requires-Dist: tqdm
Requires-Dist: numba
Requires-Dist: enum34 ; python_version < "3.4"
